lightfeed/__init__.py
lightfeed/client.py
lightfeed/models.py
lightfeed-0.1.6.dist-info/METADATA
lightfeed-0.1.6.dist-info/WHEEL
lightfeed-0.1.6.dist-info/top_level.txt
lightfeed-0.1.6.dist-info/RECORD
